mcp_ssh_session/__init__.py
mcp_ssh_session/__main__.py
mcp_ssh_session/command_executor.py
mcp_ssh_session/datastructures.py
mcp_ssh_session/enhanced_executor.py
mcp_ssh_session/enhanced_server.py
mcp_ssh_session/error_handler.py
mcp_ssh_session/file_manager.py
mcp_ssh_session/logging_manager.py
mcp_ssh_session/server.py
mcp_ssh_session/session_diagnostics.py
mcp_ssh_session/session_manager.py
mcp_ssh_session/validation.py
mcp_ssh_session-0.1.9.dist-info/METADATA
mcp_ssh_session-0.1.9.dist-info/WHEEL
mcp_ssh_session-0.1.9.dist-info/entry_points.txt
mcp_ssh_session-0.1.9.dist-info/licenses/LICENSE
mcp_ssh_session-0.1.9.dist-info/RECORD
