Metadata-Version: 2.4
Name: mcp-ssh-session
Version: 0.1.9
Summary: MCP server for managing persistent SSH sessions
Project-URL: Homepage, https://github.com/devnullvoid/mcp-ssh-session
Project-URL: Repository, https://github.com/devnullvoid/mcp-ssh-session
Project-URL: Issues, https://github.com/devnullvoid/mcp-ssh-session/issues
Author: Jon Rogers <devnullvoid>
License: Copyright © 2025 Jon Rogers
License-File: LICENSE
Keywords: cli,fastmcp,mcp,ssh
Classifier: Development Status :: 4 - Beta
Classifier: Environment :: Console
Classifier: Intended Audience :: Developers
Classifier: License :: OSI Approved :: MIT License
Classifier: Operating System :: OS Independent
Classifier: Programming Language :: Python
Classifier: Programming Language :: Python :: 3
Classifier: Programming Language :: Python :: 3.10
Classifier: Programming Language :: Python :: 3.11
Classifier: Programming Language :: Python :: 3.12
Classifier: Topic :: System :: Networking
Classifier: Topic :: System :: Systems Administration
Requires-Python: >=3.10
Requires-Dist: fastmcp
Requires-Dist: paramiko>=3.4.0
Requires-Dist: pyte>=0.8.0
